odoo/addons/helpdesk_type_sla/README.rst
odoo/addons/helpdesk_type_sla/__init__.py
odoo/addons/helpdesk_type_sla/__manifest__.py
odoo/addons/helpdesk_type_sla/i18n/es.po
odoo/addons/helpdesk_type_sla/i18n/es_AR.po
odoo/addons/helpdesk_type_sla/i18n/helpdesk_type_sla.pot
odoo/addons/helpdesk_type_sla/i18n/it.po
odoo/addons/helpdesk_type_sla/i18n/pt.po
odoo/addons/helpdesk_type_sla/models/__init__.py
odoo/addons/helpdesk_type_sla/models/helpdesk_sla.py
odoo/addons/helpdesk_type_sla/models/helpdesk_ticket.py
odoo/addons/helpdesk_type_sla/readme/CONTRIBUTORS.md
odoo/addons/helpdesk_type_sla/readme/DESCRIPTION.md
odoo/addons/helpdesk_type_sla/static/description/icon.png
odoo/addons/helpdesk_type_sla/static/description/index.html
odoo/addons/helpdesk_type_sla/tests/__init__.py
odoo/addons/helpdesk_type_sla/tests/test_helpdesk_mgmt_sla_type.py
odoo/addons/helpdesk_type_sla/views/helpdesk_sla_views.xml
odoo_addon_helpdesk_type_sla-18.0.1.0.0.7.dist-info/METADATA
odoo_addon_helpdesk_type_sla-18.0.1.0.0.7.dist-info/WHEEL
odoo_addon_helpdesk_type_sla-18.0.1.0.0.7.dist-info/top_level.txt
odoo_addon_helpdesk_type_sla-18.0.1.0.0.7.dist-info/RECORD
