Metadata-Version: 2.1
Name: odoo-addon-helpdesk_type_sla
Version: 18.0.1.0.0.7
Requires-Python: >=3.10
Requires-Dist: odoo-addon-helpdesk_mgmt_sla==18.0.*
Requires-Dist: odoo-addon-helpdesk_type==18.0.*
Requires-Dist: odoo==18.0.*
Summary: Helpdesk Type SLA
Home-page: https://github.com/OCA/helpdesk
License: AGPL-3
Author: Camptocamp, Odoo Community Association (OCA)
Author-email: support@odoo-community.org
Classifier: Programming Language :: Python
Classifier: Framework :: Odoo
Classifier: Framework :: Odoo :: 18.0
Classifier: License :: OSI Approved :: GNU Affero General Public License v3
